my_first_messenger_server-0.0.3.data/scripts/server_run
server/__init__.py
server/server.py
server/common/__init__.py
server/common/decos_log.py
server/common/descripters.py
server/common/errors.py
server/common/metaclass.py
server/common/utils.py
server/common/variables.py
server/logs/__init__.py
server/logs/client_log_config.py
server/logs/server_log_config.py
server/server/__init__.py
server/server/add_user.py
server/server/config_window.py
server/server/core.py
server/server/main_window.py
server/server/remove_user.py
server/server/server_db.py
server/server/stat_window.py
my_first_messenger_server-0.0.3.dist-info/METADATA
my_first_messenger_server-0.0.3.dist-info/WHEEL
my_first_messenger_server-0.0.3.dist-info/top_level.txt
my_first_messenger_server-0.0.3.dist-info/RECORD
