Metadata-Version: 2.1
Name: my-first-messenger-server
Version: 0.0.3
Summary: Messenger Server
Home-page: UNKNOWN
Author: Aleksandr
Author-email: aleksander.17047665@gmail.com
License: UNKNOWN
Platform: UNKNOWN
Requires-Dist: PyQt5
Requires-Dist: sqlalchemy
Requires-Dist: pycryptodome
Requires-Dist: pycryptodomex
